nfv_manager-1.3.3.data/scripts/nfv-manager
eu/__init__.py
eu/softfire/__init__.py
eu/softfire/nfv/__init__.py
eu/softfire/nfv/main/__init__.py
eu/softfire/nfv/main/Manager.py
eu/softfire/nfv/core/__init__.py
eu/softfire/nfv/core/NfvManager.py
eu/softfire/nfv/utils/__init__.py
eu/softfire/nfv/utils/static_config.py
eu/softfire/nfv/utils/utils.py
eu/softfire/nfv/utils/exceptions.py
eu/softfire/nfv/utils/os_utils.py
eu/softfire/nfv/utils/ob_utils.py
eu/softfire/nfv/db/__init__.py
eu/softfire/nfv/db/entities.py
eu/softfire/nfv/db/repositories.py
nfv_manager-1.3.3.dist-info/METADATA
nfv_manager-1.3.3.dist-info/WHEEL
nfv_manager-1.3.3.dist-info/top_level.txt
nfv_manager-1.3.3.dist-info/DESCRIPTION.rst
nfv_manager-1.3.3.dist-info/RECORD
nfv_manager-1.3.3.dist-info/metadata.json
tests/__init__.py
tests/ob_test.py
tests/test_os_utils.py
