Metadata-Version: 2.0
Name: nfv-manager
Version: 1.3.3
Summary: The SoftFIRE NFV Manager
Home-page: http://softfire.eu/
Author: SoftFIRE
Author-email: softfire@softfire.eu
License: Apache 2
Keywords: python vnfm nfvo open baton openbaton sdk experiment manager softfire tosca openstack rest
Platform: UNKNOWN
Classifier: Development Status :: 4 - Beta
Classifier: Intended Audience :: Developers
Classifier: License :: OSI Approved :: Apache Software License
Requires-Dist: asyncio
Requires-Dist: grpcio
Requires-Dist: openbaton-cli (==5.0.1)
Requires-Dist: python-keystoneclient
Requires-Dist: python-neutronclient
Requires-Dist: python-glanceclient
Requires-Dist: python-novaclient
Requires-Dist: softfire-sdk (==1.1.4)
Requires-Dist: sqlalchemy
